logger.py
mcp_server.py
mseep_instagram_dm_mcp-0.1.1.dist-info/licenses/LICENSE
mseep_instagram_dm_mcp-0.1.1.dist-info/METADATA
mseep_instagram_dm_mcp-0.1.1.dist-info/WHEEL
mseep_instagram_dm_mcp-0.1.1.dist-info/top_level.txt
mseep_instagram_dm_mcp-0.1.1.dist-info/RECORD
