Metadata-Version: 2.4
Name: mseep-instagram-dm-mcp
Version: 0.1.1
Summary: Add your description here
Author-email: mseep <support@skydeck.ai>
Requires-Python: >=3.10
License-File: LICENSE
Requires-Dist: annotated-types==0.7.0
Requires-Dist: anyio==4.9.0
Requires-Dist: authlib==1.6.0
Requires-Dist: certifi==2025.6.15
Requires-Dist: cffi==1.17.1
Requires-Dist: charset-normalizer==3.4.2
Requires-Dist: click==8.2.1
Requires-Dist: cryptography==45.0.4
Requires-Dist: exceptiongroup==1.3.0
Requires-Dist: fastmcp==2.8.1
Requires-Dist: h11==0.16.0
Requires-Dist: httpcore==1.0.9
Requires-Dist: httpx==0.28.1
Requires-Dist: httpx-sse==0.4.0
Requires-Dist: idna==3.10
Requires-Dist: instagrapi==2.1.5
Requires-Dist: markdown-it-py==3.0.0
Requires-Dist: mcp==1.9.4
Requires-Dist: mdurl==0.1.2
Requires-Dist: openapi-pydantic==0.5.1
Requires-Dist: pillow>=8.1.1
Requires-Dist: pycparser==2.22
Requires-Dist: pycryptodomex==3.23.0
Requires-Dist: pydantic==2.11.5
Requires-Dist: pydantic-core==2.33.2
Requires-Dist: pydantic-settings==2.9.1
Requires-Dist: pygments==2.19.1
Requires-Dist: pysocks==1.7.1
Requires-Dist: python-dotenv==1.1.0
Requires-Dist: python-multipart==0.0.20
Requires-Dist: requests==2.32.4
Requires-Dist: rich==14.0.0
Requires-Dist: shellingham==1.5.4
Requires-Dist: sniffio==1.3.1
Requires-Dist: sse-starlette==2.3.6
Requires-Dist: starlette==0.47.0
Requires-Dist: typer==0.16.0
Requires-Dist: typing-extensions==4.14.0
Requires-Dist: typing-inspection==0.4.1
Requires-Dist: urllib3==2.5.0
Requires-Dist: uvicorn==0.34.3
Dynamic: license-file
